{"date":"260602","isoDate":"2026-06-02","weekday":"Tue","title":"NY Times, Tue, Jun 2, 2026","author":"Hal Moore","editor":"Will Shortz","width":15,"height":15,"grid":[[{"solution":"A","number":1},{"solution":"C","number":2},{"solution":"H","number":3},{"solution":"Y","number":4},{"black":true},{"black":true},{"solution":"O","number":5},{"solution":"P","number":6},{"solution":"I","number":7},{"black":true},{"solution":"T","number":8},{"solution":"A","number":9},{"solution":"C","number":10},{"solution":"O","number":11},{"solution":"S","number":12}],[{"solution":"C","number":13},{"solution":"H"},{"solution":"E"},{"solution":"E"},{"solution":"R","number":14},{"black":true},{"solution":"W","number":15},{"solution":"A"},{"solution":"T"},{"solution":"E","number":16},{"solution":"R"},{"solution":"P"},{"solution":"O"},{"solution":"L"},{"solution":"O"}],[{"solution":"T","number":17},{"solution":"I"},{"solution":"E"},{"solution":"S"},{"solution":"U"},{"solution":"P","number":18},{"solution":"L"},{"solution":"O"},{"solution":"O"},{"solution":"S"},{"solution":"E"},{"solution":"E"},{"solution":"N"},{"solution":"D"},{"solution":"S"}],[{"solution":"S","number":19},{"solution":"A"},{"solution":"L"},{"solution":"I"},{"solution":"N"},{"solution":"E"},{"black":true},{"solution":"L","number":20},{"solution":"O"},{"solution":"T"},{"black":true},{"black":true},{"solution":"T","number":21},{"solution":"E"},{"solution":"A"}],[{"black":true},{"black":true},{"black":true},{"solution":"A","number":22},{"solution":"D"},{"solution":"D"},{"solution":"T","number":23},{"solution":"O"},{"black":true},{"solution":"A","number":24},{"solution":"S","number":25},{"solution":"K","number":26},{"solution":"I"},{"solution":"N"},{"black":true}],[{"solution":"G","number":27},{"solution":"R","number":28},{"solution":"A","number":29},{"solution":"M"},{"solution":"M"},{"solution":"A"},{"solution":"R"},{"black":true},{"solution":"S","number":30},{"solution":"T"},{"solution":"E"},{"solution":"R"},{"solution":"N"},{"black":true},{"black":true}],[{"solution":"L","number":31},{"solution":"O"},{"solution":"X"},{"black":true},{"solution":"C","number":32},{"solution":"L"},{"solution":"O"},{"solution":"S","number":33},{"solution":"E"},{"solution":"E"},{"solution":"N"},{"solution":"O"},{"solution":"U"},{"solution":"G","number":34},{"solution":"H","number":35}],[{"solution":"A","number":36},{"solution":"T"},{"solution":"I"},{"solution":"T","number":37},{"black":true},{"black":true},{"solution":"O","number":38},{"solution":"A"},{"solution":"R"},{"black":true},{"black":true},{"solution":"C","number":39},{"solution":"I"},{"solution":"A"},{"solution":"O"}],[{"solution":"M","number":40},{"solution":"I"},{"solution":"S"},{"solution":"E"},{"solution":"E","number":41},{"solution":"N","number":42},{"solution":"P"},{"solution":"L"},{"solution":"A"},{"solution":"C","number":43},{"solution":"E","number":44},{"black":true},{"solution":"T","number":45},{"solution":"I"},{"solution":"P"}],[{"black":true},{"black":true},{"solution":"P","number":46},{"solution":"E"},{"solution":"S"},{"solution":"O"},{"solution":"S"},{"black":true},{"solution":"P","number":47},{"solution":"A"},{"solution":"P"},{"solution":"A","number":48},{"solution":"Y"},{"solution":"A"},{"solution":"S"}],[{"black":true},{"solution":"P","number":49},{"solution":"O"},{"solution":"S"},{"solution":"T"},{"solution":"S"},{"black":true},{"solution":"S","number":50},{"solution":"E"},{"solution":"N"},{"solution":"O"},{"solution":"R"},{"black":true},{"black":true},{"black":true}],[{"solution":"P","number":51},{"solution":"E"},{"solution":"W"},{"black":true},{"black":true},{"solution":"I","number":52},{"solution":"O","number":53},{"solution":"U"},{"black":true},{"solution":"S","number":54},{"solution":"C"},{"solution":"R"},{"solution":"I","number":55},{"solution":"B","number":56},{"solution":"E","number":57}],[{"solution":"S","number":58},{"solution":"E"},{"solution":"E"},{"solution":"N","number":59},{"solution":"A","number":60},{"solution":"N"},{"solution":"D"},{"solution":"N"},{"solution":"O","number":61},{"solution":"T"},{"solution":"H"},{"solution":"E"},{"solution":"A"},{"solution":"R"},{"solution":"D"}],[{"solution":"S","number":62},{"solution":"T"},{"solution":"R"},{"solution":"I"},{"solution":"N"},{"solution":"G"},{"solution":"E"},{"solution":"N"},{"solution":"T"},{"black":true},{"solution":"S","number":63},{"solution":"A"},{"solution":"G"},{"solution":"A"},{"solution":"N"}],[{"solution":"T","number":64},{"solution":"E"},{"solution":"S"},{"solution":"T"},{"solution":"Y"},{"black":true},{"solution":"S","number":65},{"solution":"I"},{"solution":"C"},{"black":true},{"black":true},{"solution":"R","number":66},{"solution":"O"},{"solution":"S"},{"solution":"A"}]],"clues":{"across":[{"number":1,"clue":"Sore","answer":"ACHY","row":0,"col":0,"len":4},{"number":5,"clue":"Nail polish brand","answer":"OPI","row":0,"col":6,"len":3},{"number":8,"clue":"Some cantina fare","answer":"TACOS","row":0,"col":10,"len":5},{"number":13,"clue":"\"Hip hip hooray!,\" e.g.","answer":"CHEER","row":1,"col":0,"len":5},{"number":15,"clue":"Sink-or-swim competition?","answer":"WATERPOLO","row":1,"col":6,"len":9},{"number":17,"clue":"Handles a few unresolved issues","answer":"TIESUPLOOSEENDS","row":2,"col":0,"len":15},{"number":19,"clue":"Like tears","answer":"SALINE","row":3,"col":0,"len":6},{"number":20,"clue":"Site to build on","answer":"LOT","row":3,"col":7,"len":3},{"number":21,"clue":"Gossip, slangily","answer":"TEA","row":3,"col":12,"len":3},{"number":22,"clue":"Build on","answer":"ADDTO","row":4,"col":3,"len":5},{"number":24,"clue":"Welcome at the door, say","answer":"ASKIN","row":4,"col":9,"len":5},{"number":27,"clue":"Linguist's concern","answer":"GRAMMAR","row":5,"col":0,"len":7},{"number":30,"clue":"Serious in manner","answer":"STERN","row":5,"col":8,"len":5},{"number":31,"clue":"Bagel topping","answer":"LOX","row":6,"col":0,"len":3},{"number":32,"clue":"Not perfect, but acceptable","answer":"CLOSEENOUGH","row":6,"col":4,"len":11},{"number":36,"clue":"Bickering","answer":"ATIT","row":7,"col":0,"len":4},{"number":38,"clue":"Blade that's pulled","answer":"OAR","row":7,"col":6,"len":3},{"number":39,"clue":"Casual farewell often used outside its language of origin","answer":"CIAO","row":7,"col":11,"len":4},{"number":40,"clue":"Station set up in a kitchen","answer":"MISEENPLACE","row":8,"col":0,"len":11},{"number":45,"clue":"Bit of intel","answer":"TIP","row":8,"col":12,"len":3},{"number":46,"clue":"Coins of Cuba","answer":"PESOS","row":9,"col":2,"len":5},{"number":47,"clue":"Ingredients in some tropical smoothies","answer":"PAPAYAS","row":9,"col":8,"len":7},{"number":49,"clue":"Foreign Service assignments","answer":"POSTS","row":10,"col":1,"len":5},{"number":50,"clue":"Madrid mister","answer":"SENOR","row":10,"col":7,"len":5},{"number":51,"clue":"Church seat","answer":"PEW","row":11,"col":0,"len":3},{"number":52,"clue":"Promise to pay","answer":"IOU","row":11,"col":5,"len":3},{"number":54,"clue":"Journalist, informally","answer":"SCRIBE","row":11,"col":9,"len":6},{"number":58,"clue":"Like children, ideally, in an old adage ... or a hint to a four-letter word hidden in 17-, 32- and 40-Across","answer":"SEENANDNOTHEARD","row":12,"col":0,"len":15},{"number":62,"clue":"Rigorous","answer":"STRINGENT","row":13,"col":0,"len":9},{"number":63,"clue":"Astronomer Carl","answer":"SAGAN","row":13,"col":10,"len":5},{"number":64,"clue":"Irritable","answer":"TESTY","row":14,"col":0,"len":5},{"number":65,"clue":"[As written]","answer":"SIC","row":14,"col":6,"len":3},{"number":66,"clue":"Civil rights activist Parks","answer":"ROSA","row":14,"col":11,"len":4}],"down":[{"number":1,"clue":"Play parts","answer":"ACTS","row":0,"col":0,"len":4},{"number":2,"clue":"Kind of seed or pet","answer":"CHIA","row":0,"col":1,"len":4},{"number":3,"clue":"Sometimes-raised part of a shoe","answer":"HEEL","row":0,"col":2,"len":4},{"number":4,"clue":"Emphatic confirmation","answer":"YESIAM","row":0,"col":3,"len":6},{"number":5,"clue":"Nocturnal hooter","answer":"OWL","row":0,"col":6,"len":3},{"number":6,"clue":"Painter Veronese","answer":"PAOLO","row":0,"col":7,"len":5},{"number":7,"clue":"Langston Hughes poem","answer":"ITOO","row":0,"col":8,"len":4},{"number":8,"clue":"Due + 1","answer":"TRE","row":0,"col":10,"len":3},{"number":9,"clue":"Mimic","answer":"APE","row":0,"col":11,"len":3},{"number":10,"clue":"Script supervisor's concern","answer":"CONTINUITY","row":0,"col":12,"len":10},{"number":11,"clue":"___ days","answer":"OLDEN","row":0,"col":13,"len":5},{"number":12,"clue":"Slugger Sammy","answer":"SOSA","row":0,"col":14,"len":4},{"number":14,"clue":"\"Raising Hell\" rap trio","answer":"RUNDMC","row":1,"col":4,"len":6},{"number":16,"clue":"Council ___ (British equivalent of a housing project)","answer":"ESTATE","row":1,"col":9,"len":6},{"number":18,"clue":"Part of a piano or loom","answer":"PEDAL","row":2,"col":5,"len":5},{"number":23,"clue":"Boots on the ground","answer":"TROOPS","row":4,"col":6,"len":6},{"number":25,"clue":"Rep.'s counterpart","answer":"SEN","row":4,"col":10,"len":3},{"number":26,"clue":"Ray of McDonald's","answer":"KROC","row":4,"col":11,"len":4},{"number":27,"clue":"Genre for Ziggy Stardust, informally","answer":"GLAM","row":5,"col":0,"len":4},{"number":28,"clue":"Naan alternative","answer":"ROTI","row":5,"col":1,"len":4},{"number":29,"clue":"Coalition that opposed the Allies in W.W. II","answer":"AXISPOWERS","row":5,"col":2,"len":10},{"number":30,"clue":"Mexican wrap","answer":"SERAPE","row":5,"col":8,"len":6},{"number":33,"clue":"Kid-lit girl with a blueberry pail","answer":"SAL","row":6,"col":7,"len":3},{"number":34,"clue":"Greek goddess of the earth","answer":"GAIA","row":6,"col":13,"len":4},{"number":35,"clue":"Brewing need","answer":"HOPS","row":6,"col":14,"len":4},{"number":37,"clue":"They help you drive farther","answer":"TEES","row":7,"col":3,"len":4},{"number":41,"clue":"Ballpark fig.","answer":"EST","row":8,"col":4,"len":3},{"number":42,"clue":"Snooping (around)","answer":"NOSING","row":8,"col":5,"len":6},{"number":43,"clue":"\"___ thou not minister to a mind diseased ...?\": Macbeth","answer":"CANST","row":8,"col":9,"len":5},{"number":44,"clue":"Significant periods","answer":"EPOCHS","row":8,"col":10,"len":6},{"number":48,"clue":"Overdue debt","answer":"ARREAR","row":9,"col":11,"len":6},{"number":49,"clue":"Golfer Calvin or QB Rodney","answer":"PEETE","row":10,"col":1,"len":5},{"number":50,"clue":"Islam's largest branch","answer":"SUNNI","row":10,"col":7,"len":5},{"number":51,"clue":"Alternative to a tap on the shoulder","answer":"PSST","row":11,"col":0,"len":4},{"number":53,"clue":"Works of praise","answer":"ODES","row":11,"col":6,"len":4},{"number":55,"clue":"\"Othello\" villain","answer":"IAGO","row":11,"col":12,"len":4},{"number":56,"clue":"Some supports","answer":"BRAS","row":11,"col":13,"len":4},{"number":57,"clue":"___ Lewis, the \"Grande Dame of Southern Cooking\"","answer":"EDNA","row":11,"col":14,"len":4},{"number":59,"clue":"Minor complaint","answer":"NIT","row":12,"col":3,"len":3},{"number":60,"clue":"Unspecified amount","answer":"ANY","row":12,"col":4,"len":3},{"number":61,"clue":"Not Rx","answer":"OTC","row":12,"col":8,"len":3}]}}