{"source":"nyt","date":"260523","isoDate":"2026-05-23","weekday":"Sat","title":"NY Times, Sat, May 23, 2026","author":"Jesse Cohn","editor":"Will Shortz","width":15,"height":15,"grid":[[{"black":true},{"black":true},{"black":true},{"solution":"S","number":1},{"solution":"P","number":2},{"solution":"I","number":3},{"solution":"N","number":4},{"solution":"O","number":5},{"solution":"F","number":6},{"solution":"F","number":7},{"black":true},{"solution":"B","number":8},{"solution":"A","number":9},{"solution":"M","number":10},{"solution":"A","number":11}],[{"black":true},{"black":true},{"solution":"S","number":12},{"solution":"O"},{"solution":"O"},{"solution":"N"},{"solution":"E"},{"solution":"R"},{"solution":"O"},{"solution":"R"},{"solution":"L","number":13},{"solution":"A"},{"solution":"T"},{"solution":"E"},{"solution":"R"}],[{"black":true},{"solution":"C","number":14},{"solution":"A"},{"solution":"L"},{"solution":"I"},{"solution":"F"},{"solution":"O"},{"solution":"R"},{"solution":"N"},{"solution":"I"},{"solution":"A"},{"solution":"R"},{"solution":"O"},{"solution":"L"},{"solution":"L"}],[{"black":true},{"solution":"H","number":15},{"solution":"U"},{"solution":"D"},{"solution":"S"},{"solution":"O"},{"solution":"N"},{"black":true},{"solution":"D","number":16},{"solution":"E"},{"solution":"T"},{"solution":"E"},{"solution":"N"},{"solution":"T"},{"solution":"E"}],[{"solution":"D","number":17},{"solution":"O"},{"solution":"C"},{"solution":"T"},{"solution":"O"},{"solution":"R"},{"black":true},{"solution":"M","number":18},{"solution":"O"},{"solution":"D"},{"black":true},{"solution":"F","number":19},{"solution":"E"},{"solution":"E"},{"solution":"S"}],[{"solution":"F","number":20},{"solution":"R"},{"solution":"E"},{"solution":"O"},{"solution":"N"},{"black":true},{"solution":"S","number":21},{"solution":"A"},{"solution":"F"},{"solution":"E"},{"solution":"W","number":22},{"solution":"O"},{"solution":"R"},{"solution":"D"},{"black":true}],[{"solution":"W","number":23},{"solution":"E"},{"solution":"D"},{"black":true},{"solution":"D","number":24},{"solution":"U","number":25},{"solution":"A"},{"solution":"L"},{"black":true},{"solution":"G","number":26},{"solution":"E"},{"solution":"O"},{"solution":"S"},{"black":true},{"black":true}],[{"black":true},{"black":true},{"black":true},{"solution":"H","number":27},{"solution":"A"},{"solution":"N"},{"solution":"G"},{"solution":"T"},{"solution":"I","number":28},{"solution":"G"},{"solution":"H"},{"solution":"T"},{"black":true},{"black":true},{"black":true}],[{"black":true},{"black":true},{"solution":"P","number":29},{"solution":"A"},{"solution":"R"},{"solution":"D"},{"black":true},{"solution":"E","number":30},{"solution":"L"},{"solution":"S"},{"solution":"A"},{"black":true},{"solution":"S","number":31},{"solution":"E","number":32},{"solution":"T","number":33}],[{"black":true},{"solution":"R","number":34},{"solution":"E"},{"solution":"S"},{"solution":"T"},{"solution":"E"},{"solution":"A","number":35},{"solution":"S"},{"solution":"Y"},{"black":true},{"solution":"D","number":36},{"solution":"W","number":37},{"solution":"A"},{"solution":"D"},{"solution":"E"}],[{"solution":"M","number":38},{"solution":"A"},{"solution":"T"},{"solution":"S"},{"black":true},{"solution":"C","number":39},{"solution":"L"},{"solution":"E"},{"black":true},{"solution":"M","number":40},{"solution":"A"},{"solution":"R"},{"solution":"T"},{"solution":"I"},{"solution":"N"}],[{"solution":"I","number":41},{"solution":"M"},{"solution":"F"},{"solution":"O"},{"solution":"R","number":42},{"solution":"I"},{"solution":"T"},{"black":true},{"solution":"M","number":43},{"solution":"A"},{"solution":"D"},{"solution":"E"},{"solution":"I"},{"solution":"T"},{"black":true}],[{"solution":"C","number":44},{"solution":"R"},{"solution":"O"},{"solution":"C"},{"solution":"O"},{"solution":"D"},{"solution":"I"},{"solution":"L","number":45},{"solution":"E"},{"solution":"T"},{"solution":"E"},{"solution":"A"},{"solution":"R"},{"solution":"S"},{"black":true}],[{"solution":"R","number":46},{"solution":"O"},{"solution":"O"},{"solution":"K"},{"solution":"I"},{"solution":"E"},{"solution":"M"},{"solution":"I"},{"solution":"S"},{"solution":"T"},{"solution":"A"},{"solution":"K"},{"solution":"E"},{"black":true},{"black":true}],[{"solution":"O","number":47},{"solution":"D"},{"solution":"D"},{"solution":"S"},{"black":true},{"solution":"D","number":48},{"solution":"A"},{"solution":"M"},{"solution":"S"},{"solution":"E"},{"solution":"L"},{"solution":"S"},{"black":true},{"black":true},{"black":true}]],"clues":{"across":[{"number":1,"clue":"\"The Jeffersons\" or \"The Simpsons,\" notably","answer":"SPINOFF","row":0,"col":3,"len":7},{"number":8,"clue":"Team with the mascot Big Al, familiarly","answer":"BAMA","row":0,"col":11,"len":4},{"number":12,"clue":"In time","answer":"SOONERORLATER","row":1,"col":2,"len":13},{"number":14,"clue":"Dish purportedly invented in Los Angeles's Little Tokyo neighborhood","answer":"CALIFORNIAROLL","row":2,"col":1,"len":14},{"number":15,"clue":"New York's ___ Valley","answer":"HUDSON","row":3,"col":1,"len":6},{"number":16,"clue":"Thawing","answer":"DETENTE","row":3,"col":8,"len":7},{"number":17,"clue":"Treat","answer":"DOCTOR","row":4,"col":0,"len":6},{"number":18,"clue":"New outfit or accessory for a character, in video game-speak","answer":"MOD","row":4,"col":7,"len":3},{"number":19,"clue":"Things that shouldn't be hidden","answer":"FEES","row":4,"col":11,"len":4},{"number":20,"clue":"Non-eco-friendly refrigerant","answer":"FREON","row":5,"col":0,"len":5},{"number":21,"clue":"Term in the bedroom, maybe","answer":"SAFEWORD","row":5,"col":6,"len":8},{"number":23,"clue":"Unite","answer":"WED","row":6,"col":0,"len":3},{"number":24,"clue":"Two-pronged","answer":"DUAL","row":6,"col":4,"len":4},{"number":26,"clue":"Metros in the 1990s","answer":"GEOS","row":6,"col":9,"len":4},{"number":27,"clue":"\"Wait just a sec\"","answer":"HANGTIGHT","row":7,"col":3,"len":9},{"number":29,"clue":"Cowboy's friend, informally","answer":"PARD","row":8,"col":2,"len":4},{"number":30,"clue":"Name that spiked in popularity following a 2013 Disney movie","answer":"ELSA","row":8,"col":7,"len":4},{"number":31,"clue":"Finalized","answer":"SET","row":8,"col":12,"len":3},{"number":34,"clue":"\"You've got nothing to worry about\"","answer":"RESTEASY","row":9,"col":1,"len":8},{"number":36,"clue":"All-time scoring leader for the Miami Heat, familiarly","answer":"DWADE","row":9,"col":10,"len":5},{"number":38,"clue":"Routine surfaces","answer":"MATS","row":10,"col":0,"len":4},{"number":39,"clue":"Browns, on a scoreboard","answer":"CLE","row":10,"col":5,"len":3},{"number":40,"clue":"Mathematics writer Gardner","answer":"MARTIN","row":10,"col":9,"len":6},{"number":41,"clue":"Words of endorsement","answer":"IMFORIT","row":11,"col":0,"len":7},{"number":43,"clue":"Arrived","answer":"MADEIT","row":11,"col":8,"len":6},{"number":44,"clue":"Make-believe sorrow","answer":"CROCODILETEARS","row":12,"col":0,"len":14},{"number":46,"clue":"Cause of amusement to a vet, maybe","answer":"ROOKIEMISTAKE","row":13,"col":0,"len":13},{"number":47,"clue":"Daredevil's calculation","answer":"ODDS","row":14,"col":0,"len":4},{"number":48,"clue":"Some fairy tale characters","answer":"DAMSELS","row":14,"col":5,"len":7}],"down":[{"number":1,"clue":"Did business with, in a way","answer":"SOLDTO","row":0,"col":3,"len":6},{"number":2,"clue":"Blowgun projectile","answer":"POISONDART","row":0,"col":4,"len":10},{"number":3,"clue":"Words before \"a penny\" or \"a treat\"","answer":"INFOR","row":0,"col":5,"len":5},{"number":4,"clue":"Fifth-most abundant element in the universe","answer":"NEON","row":0,"col":6,"len":4},{"number":5,"clue":"Lieutenant in \"Catch-22\"","answer":"ORR","row":0,"col":7,"len":3},{"number":6,"clue":"Into","answer":"FONDOF","row":0,"col":8,"len":6},{"number":7,"clue":"Breakfast dish that might go over well?","answer":"FRIEDEGGS","row":0,"col":9,"len":9},{"number":8,"clue":"How people get into a swimming pool, typically","answer":"BAREFOOT","row":0,"col":11,"len":8},{"number":9,"clue":"Yom Kippur observers","answer":"ATONERS","row":0,"col":12,"len":7},{"number":10,"clue":"Like the cheese in fondue","answer":"MELTED","row":0,"col":13,"len":6},{"number":11,"clue":"Backdrop for many van Gogh paintings","answer":"ARLES","row":0,"col":14,"len":5},{"number":12,"clue":"Blitzed","answer":"SAUCED","row":1,"col":2,"len":6},{"number":13,"clue":"___ pull-downs (exercise)","answer":"LAT","row":1,"col":10,"len":3},{"number":14,"clue":"Item in a list on the fridge, maybe","answer":"CHORE","row":2,"col":1,"len":5},{"number":17,"clue":"Texas air hub, for short","answer":"DFW","row":4,"col":0,"len":3},{"number":18,"clue":"Silky-haired toy","answer":"MALTESE","row":4,"col":7,"len":7},{"number":21,"clue":"Start to give","answer":"SAG","row":5,"col":6,"len":3},{"number":22,"clue":"\"Hey, no backing out now!\"","answer":"WEHADADEAL","row":5,"col":10,"len":10},{"number":25,"clue":"Still waffling","answer":"UNDECIDED","row":6,"col":5,"len":9},{"number":27,"clue":"Relatives of ottomans","answer":"HASSOCKS","row":7,"col":3,"len":8},{"number":28,"clue":"Texter's affectionate sign-off","answer":"ILY","row":7,"col":8,"len":3},{"number":29,"clue":"It's not fit for human consumption","answer":"PETFOOD","row":8,"col":2,"len":7},{"number":31,"clue":"Cutting stuff","answer":"SATIRE","row":8,"col":12,"len":6},{"number":32,"clue":"Cuts a line?","answer":"EDITS","row":8,"col":13,"len":5},{"number":33,"clue":"It takes two hands to show","answer":"TEN","row":8,"col":14,"len":3},{"number":34,"clue":"Musketeer's tool","answer":"RAMROD","row":9,"col":1,"len":6},{"number":35,"clue":"Nissan model","answer":"ALTIMA","row":9,"col":6,"len":6},{"number":37,"clue":"Brings about, as havoc","answer":"WREAKS","row":9,"col":11,"len":6},{"number":38,"clue":"Less than milli-, more than nano-","answer":"MICRO","row":10,"col":0,"len":5},{"number":40,"clue":"Paint option","answer":"MATTE","row":10,"col":9,"len":5},{"number":42,"clue":"Metric for a venture capitalist, in brief","answer":"ROI","row":11,"col":4,"len":3},{"number":43,"clue":"Play (with)","answer":"MESS","row":11,"col":8,"len":4},{"number":45,"clue":"Calc. calculation","answer":"LIM","row":12,"col":7,"len":3}]}}